__init__.py
settings_manager/__init__.py
settings_manager/main.py
pietro_settings_manager-1.0.4.dist-info/LICENSE
pietro_settings_manager-1.0.4.dist-info/METADATA
pietro_settings_manager-1.0.4.dist-info/WHEEL
pietro_settings_manager-1.0.4.dist-info/top_level.txt
pietro_settings_manager-1.0.4.dist-info/RECORD
