Metadata-Version: 2.2
Name: pietro-settings-manager
Version: 1.0.4
Summary: A Python settings manager package that allows you to make settings handling easy.
Author-email: P1etrodev <undefinedpietro@gmail.com>
Project-URL: Homepage, https://github.com/P1etrodev/settings-manager
Project-URL: Issues, https://github.com/P1etrodev/settings-manager/issues
Classifier: Programming Language :: Python :: 3
Classifier: Operating System :: OS Independent
Classifier: License :: OSI Approved :: MIT License
Requires-Python: >=3.8
License-File: LICENSE
